henmedlib/__init__.py
henmedlib/func/__init__.py
henmedlib/func/anonymise.py
henmedlib/func/command_line_related.py
henmedlib/func/directory_structure.py
henmedlib/func/hounsfield.py
henmedlib/functions/__init__.py
henmedlib/functions/anonymise.py
henmedlib/functions/command_line_related.py
henmedlib/functions/directory_structure.py
henmedlib/functions/hounsfield.py
henmedlib/i_o/__init__.py
henmedlib/i_o/dicom.py
henmedlib/i_o/mha.py
henmedlib-1.0.10.dist-info/LICENSE
henmedlib-1.0.10.dist-info/METADATA
henmedlib-1.0.10.dist-info/WHEEL
henmedlib-1.0.10.dist-info/top_level.txt
henmedlib-1.0.10.dist-info/RECORD
