Metadata-Version: 2.1
Name: henmedlib
Version: 1.0.10
Summary: Package encapsulating all functions I used during my PhD.
Home-page: https://github.com/schmitzhenninglmu/henmedlib
Author: Henning Schmitz
Author-email: H.Schmitz@physik.uni-muenchen.de 
License: MIT
Platform: UNKNOWN
Classifier: Programming Language :: Python :: 3
Classifier: License :: OSI Approved :: MIT License
Classifier: Operating System :: OS Independent
Requires-Python: >=3.6
Requires-Dist: pydicom
Requires-Dist: SimpleITK
Requires-Dist: numpy
Requires-Dist: opencv-python
